python_apiserver_client/README.md
python_apiserver_client/__init__.py
python_apiserver_client/kuberay_apis.py
python_apiserver_client/params/__init__.py
python_apiserver_client/params/cluster.py
python_apiserver_client/params/environmentvariables.py
python_apiserver_client/params/headnode.py
python_apiserver_client/params/jobsubmission.py
python_apiserver_client/params/templates.py
python_apiserver_client/params/volumes.py
python_apiserver_client/params/workernode.py
runtime_utils/__init__.py
runtime_utils/kfp_utils.py
runtime_utils/remote_jobs_utils.py
data_prep_toolkit_kfp_shared-0.2.0.dist-info/METADATA
data_prep_toolkit_kfp_shared-0.2.0.dist-info/WHEEL
data_prep_toolkit_kfp_shared-0.2.0.dist-info/top_level.txt
data_prep_toolkit_kfp_shared-0.2.0.dist-info/RECORD
